dlkp/__init__.py
dlkp/run_auto_ke.py
dlkp/config/__init__.py
dlkp/datasets/__init__.py
dlkp/datasets/pre_process.py
dlkp/kp_metrics/__init__.py
dlkp/kp_metrics/metrics.py
dlkp/models/__init__.py
dlkp/models/ke/__init__.py
dlkp/models/ke/extraction_utils.py
dlkp/models/ke/kpe.py
dlkp/models/ke/crf/__init__.py
dlkp/models/ke/crf/crf.py
dlkp/models/ke/crf/crf_trainer.py
dlkp/models/ke/crf/crf_utils.py
dlkp/models/ke/transformer/__init__.py
dlkp/models/ke/transformer/crf_models.py
dlkp/models/ke/transformer/token_classification_models.py
dlkp/models/kg/__init__.py
dlkp/models/kg/transformer/__init__.py
dlkp/models/kg/transformer/seq2seq.py
dlkp-0.0.1.dist-info/LICENSE
dlkp-0.0.1.dist-info/METADATA
dlkp-0.0.1.dist-info/WHEEL
dlkp-0.0.1.dist-info/top_level.txt
dlkp-0.0.1.dist-info/RECORD
